wasteland/__init__.py
wasteland/wasteland_sort.py
wasteland_sort-1.1.0.dist-info/LICENSE
wasteland_sort-1.1.0.dist-info/METADATA
wasteland_sort-1.1.0.dist-info/WHEEL
wasteland_sort-1.1.0.dist-info/top_level.txt
wasteland_sort-1.1.0.dist-info/RECORD
