Metadata-Version: 2.1
Name: wasteland-sort
Version: 1.1.0
Summary: Fully tested and documented version of the Wasteland sorting algorithm
Home-page: https://github.com/MHromiak/wasteland_sort.git
Author: Markian Hromiak
Author-email: markian.hromiak@yahoo.com
License: UNKNOWN
Platform: UNKNOWN
Classifier: Programming Language :: Python :: 3
Classifier: License :: OSI Approved :: GNU General Public License (GPL)
Classifier: Operating System :: OS Independent
Requires-Python: >=3.8.2
